MANIFEST.in
README.md
setup.py
pythonkss/__init__.py
pythonkss/comment.py
pythonkss/example.py
pythonkss/exceptions.py
pythonkss/markdownformatter.py
pythonkss/parser.py
pythonkss/section.py
pythonkss/sectiontree.py
pythonkss/version.json
pythonkss.egg-info/PKG-INFO
pythonkss.egg-info/SOURCES.txt
pythonkss.egg-info/dependency_links.txt
pythonkss.egg-info/not-zip-safe
pythonkss.egg-info/requires.txt
pythonkss.egg-info/top_level.txt