Metadata-Version: 1.1
Name: pythonkss
Version: 1.3
Summary: Python implementation of KSS
Home-page: https://github.com/appressoas/pythonkss
Author: Espen Angell Kristiansen
Author-email: espen@appresso.no
License: BSD
Platform: UNKNOWN
Classifier: Development Status :: 4 - Beta
Classifier: Environment :: Web Environment
Classifier: Intended Audience :: Developers
Classifier: License :: OSI Approved :: BSD License
Classifier: Operating System :: OS Independent
Classifier: Programming Language :: Python
